window_art/__init__.py
window_art/animate.py
window_art/color.py
window_art/core.py
window_art/easing.py
window_art/layout.py
window_art/vec.py
window_art/window.py
window_art/media/__init__.py
window_art/media/gif.py
window_art/media/text.py
window_art/media/video.py
window_art-0.1.0.dist-info/METADATA
window_art-0.1.0.dist-info/WHEEL
window_art-0.1.0.dist-info/licenses/LICENSE
window_art-0.1.0.dist-info/RECORD
