Metadata-Version: 2.4
Name: window-art
Version: 0.1.0
Summary: A minimal Python library for live coding visual scenes using desktop windows
Project-URL: Homepage, https://github.com/willmeyers/window-art
Project-URL: Repository, https://github.com/willmeyers/window-art
Author: Window Art Contributors
License-Expression: MIT
License-File: LICENSE
Keywords: animation,creative-coding,desktop,live-coding,visual,windows
Classifier: Development Status :: 3 - Alpha
Classifier: Intended Audience :: Developers
Classifier: License :: OSI Approved :: MIT License
Classifier: Programming Language :: Python :: 3
Classifier: Programming Language :: Python :: 3.10
Classifier: Programming Language :: Python :: 3.11
Classifier: Programming Language :: Python :: 3.12
Classifier: Topic :: Multimedia :: Graphics
Requires-Python: >=3.10
Requires-Dist: pillow>=12.1.0
Requires-Dist: pysdl2-dll>=2.28.0
Requires-Dist: pysdl2>=0.9.16
Provides-Extra: dev
Requires-Dist: mypy>=1.0; extra == 'dev'
Requires-Dist: opencv-python>=4.10.0; extra == 'dev'
Requires-Dist: pytest>=7.0; extra == 'dev'
Provides-Extra: docs
Requires-Dist: mkdocs-material>=9.0; extra == 'docs'
Requires-Dist: mkdocs>=1.5; extra == 'docs'
Requires-Dist: mkdocstrings[python]>=0.24; extra == 'docs'
Provides-Extra: video
Requires-Dist: opencv-python>=4.10.0; extra == 'video'
